sconstool_nbconvert/__init__.py
sconstool_nbconvert-0.0.1.dist-info/LICENSE
sconstool_nbconvert-0.0.1.dist-info/METADATA
sconstool_nbconvert-0.0.1.dist-info/WHEEL
sconstool_nbconvert-0.0.1.dist-info/top_level.txt
sconstool_nbconvert-0.0.1.dist-info/RECORD
