Metadata-Version: 2.1
Name: sconstool-nbconvert
Version: 0.0.1
Summary: SCons tool for Jupyter notebook
Home-page: https://github.com/spielhuus/sconstool-nbconvert
Author: spielhuus
Author-email: spielhuus@gmail.com
License: UNKNOWN
Project-URL: Bug Tracker, https://github.com/spielhuus/sconstool-nbconvert/issues
Platform: UNKNOWN
Classifier: Programming Language :: Python :: 3
Classifier: License :: OSI Approved :: MIT License
Classifier: Operating System :: OS Independent
Requires-Python: >=3.10
License-File: LICENSE
Requires-Dist: matplotlib
Requires-Dist: numpy
Requires-Dist: ipython
Requires-Dist: notebook
Requires-Dist: scons
